README.md
setup.py
starlette_cli.py
starlette_cli.egg-info/PKG-INFO
starlette_cli.egg-info/SOURCES.txt
starlette_cli.egg-info/dependency_links.txt
starlette_cli.egg-info/requires.txt
starlette_cli.egg-info/top_level.txt