Metadata-Version: 2.1
Name: starlette-cli
Version: 0.1.0
Summary: make your project a cli too!
Home-page: https://yourlabs.io/oss/starlette-cli
Author: James Pic
Author-email: jamespic@gmail.com
License: MIT
Keywords: starlette cli
Platform: UNKNOWN
Requires-Python: >=3
